{
    "type": "FeatureCollection",
    "features": [
      {
        "type": "Feature",
        "geometry": {
          "type": "Point",
          "coordinates": [
            32.7256175,
            0.3740605,
            0
          ]
        },
        "properties": {
          "name": "Najeera station",
          "description": "{\"@type\":\"html\",\"value\":\"<img src=\\\"https://mymaps.usercontent.google.com/hostedimage/m/*/3AEDAZkqu4LYBjrlzIW4TkzfmjByJH2MwCvCWuSPLEmBpYTz6s1_-AL2jCv5rjAxq159UUAi-U4EDK7KpVGH6MAiCLC6DGyYj4o9GQm7BGjZABUciFXa4M4NEf34qVuGJyQwn4aySrf5udPF60GhFEpzV_mLp_hawUJ0H2qmZZtHafFVewjoSSgtzf7cQlXh0CKWe5eX7m-v9f9UVIr5T7gytBT4NXbbAl8lwjKwVGIfF-2cvNBghVUo6z048zIc?authuser=0&fife=s16383\\\" height=\\\"200\\\" width=\\\"auto\\\" /><br><br>\"}",
          "styleUrl": "#icon-1899-DB4436",
          "icon-opacity": 1,
          "icon-color": "#db4436",
          "icon-scale": 1,
          "icon-offset": "[32,64]",
          "icon-offset-units": "[\"pixels\",\"insetPixels\"]",
          "icon": "https://www.gstatic.com/mapspro/images/stock/503-wht-blank_maps.png",
          "gx_media_links": "https://mymaps.usercontent.google.com/hostedimage/m/*/3AEDAZkqu4LYBjrlzIW4TkzfmjByJH2MwCvCWuSPLEmBpYTz6s1_-AL2jCv5rjAxq159UUAi-U4EDK7KpVGH6MAiCLC6DGyYj4o9GQm7BGjZABUciFXa4M4NEf34qVuGJyQwn4aySrf5udPF60GhFEpzV_mLp_hawUJ0H2qmZZtHafFVewjoSSgtzf7cQlXh0CKWe5eX7m-v9f9UVIr5T7gytBT4NXbbAl8lwjKwVGIfF-2cvNBghVUo6z048zIc?authuser=0&fife=s16383"
        },
        "id": 0
      },
      {
        "type": "Feature",
        "geometry": {
          "type": "Point",
          "coordinates": [
            32.3525442,
            0.5058866,
            0
          ]
        },
        "properties": {
          "name": "Mityana station",
          "styleUrl": "#icon-1899-DB4436-nodesc",
          "icon-opacity": 1,
          "icon-color": "#db4436",
          "icon-scale": 1,
          "icon-offset": [
            32,
            64
          ],
          "icon-offset-units": [
            "pixels",
            "insetPixels"
          ],
          "icon": "https://www.gstatic.com/mapspro/images/stock/503-wht-blank_maps.png"
        }
      },
      {
        "type": "Feature",
        "geometry": {
          "type": "Point",
          "coordinates": [
            32.632822,
            0.8673577,
            0
          ]
        },
        "properties": {
          "name": "Upper central",
          "styleUrl": "#icon-1899-E65100-nodesc",
          "icon-opacity": 1,
          "icon-color": "#e65100",
          "icon-scale": 1,
          "icon-offset": [
            32,
            64
          ],
          "icon-offset-units": [
            "pixels",
            "insetPixels"
          ],
          "icon": "https://www.gstatic.com/mapspro/images/stock/503-wht-blank_maps.png"
        }
      }
    ]
  }